projetoRedes/__init__.py
projetoRedes/checkBin.py
projetoRedes-0.0.1.dist-info/LICENCE
projetoRedes-0.0.1.dist-info/METADATA
projetoRedes-0.0.1.dist-info/WHEEL
projetoRedes-0.0.1.dist-info/top_level.txt
projetoRedes-0.0.1.dist-info/RECORD
